pdf_question_spacer/__init__.py
pdf_question_spacer/space_pdf.py
pdf_question_spacer/text_row_extractors.py
pdf_question_spacer/text_row_filters.py
pdf_question_spacer/whitespace_inserter.py
pdf_question_spacer-1.0.2.data/scripts/space-pdf-interactive
tests/__init__.py
tests/text_row_extractors_test.py
tests/text_row_filters_test.py
tests/whitespace_insert_test.py
pdf_question_spacer-1.0.2.dist-info/LICENSE
pdf_question_spacer-1.0.2.dist-info/METADATA
pdf_question_spacer-1.0.2.dist-info/WHEEL
pdf_question_spacer-1.0.2.dist-info/entry_points.txt
pdf_question_spacer-1.0.2.dist-info/top_level.txt
pdf_question_spacer-1.0.2.dist-info/RECORD
